irLib/__init__.py
irLib/helpers/__init__.py
irLib/helpers/portfolio.py
irLib/helpers/reader.py
irLib/helpers/schedule.py
irLib/helpers/volatilityCube.py
irLib/helpers/yieldCurve.py
irLib/instruments/__init__.py
irLib/instruments/instrument.py
irLib/instruments/legs.py
irLib/instruments/option.py
irLib/instruments/swap.py
irLib/instruments/swaption.py
irLib/marketConvention/__init__.py
irLib/marketConvention/compounding.py
irLib/marketConvention/dayCount.py
irLib/marketConvention/roll.py
irLib/mathTools/__init__.py
irLib/mathTools/estimationEngine.py
irLib/mathTools/nonLinearSolver.py
irLib/mathTools/pricingEngine.py
irLib/tests/__init__.py
irLib/tests/integration_tests/__init__.py
irLib/tests/integration_tests/testLegs.py
irLib/tests/integration_tests/testSchedule.py
irLib/tests/integration_tests/testSwaption.py
irLib/tests/integration_tests/testVanillaSwap.py
irLib/tests/integration_tests/testYieldCurve.py
irLib/tests/unit_tests/__init__.py
irLib/tests/unit_tests/helpers/__init__.py
irLib/tests/unit_tests/instruments/__init__.py
irLib/tests/unit_tests/marketConvention/__init__.py
irLib/tests/unit_tests/marketConvention/testCompounding.py
irLib/tests/unit_tests/marketConvention/testDayCount.py
irLib/tests/unit_tests/marketConvention/testRoll.py
irLib/tests/unit_tests/mathTools/__init__.py
irLib/tests/unit_tests/mathTools/testPricingEngine.py
interestRateInstrumentsLib-0.4.0.dist-info/METADATA
interestRateInstrumentsLib-0.4.0.dist-info/WHEEL
interestRateInstrumentsLib-0.4.0.dist-info/top_level.txt
interestRateInstrumentsLib-0.4.0.dist-info/RECORD
