Metadata-Version: 2.1
Name: interestRateInstrumentsLib
Version: 0.4.0
Summary: Interest rate instruments library
Home-page: https://github.com/neoyung/irLib
Author: Neo Yung
Author-email: reverie211@gmail.com
License: UNKNOWN
Platform: UNKNOWN
Classifier: Programming Language :: Python :: 3
Classifier: License :: OSI Approved :: MIT License
Classifier: Operating System :: OS Independent
Requires-Python: >=3.6
Requires-Dist: convertdate
Requires-Dist: holidays
Requires-Dist: korean-lunar-calendar
Requires-Dist: numpy
Requires-Dist: pandas
Requires-Dist: PyMeeus
Requires-Dist: python-dateutil
Requires-Dist: pytz
Requires-Dist: scipy
Requires-Dist: six
Requires-Dist: toml
